<?xml version="1.0" encoding="utf-8"?>
<?xml-stylesheet type="text/xsl" href="../XSLT/decoder.xsl"?>
<!-- Copyright (C) JMRI 2026 All rights reserved -->
<enumVal xmlns:xi="http://www.w3.org/2001/XInclude" xmlns:xsi="http://www.w3.org/2001/XMLSchema-instance" xsi:noNamespaceSchemaLocation="http://jmri.org/xml/schema/decoder-4-15-2.xsd">
    <enumChoice choice="0 – Deactivated" value="0">
        <choice>0 – Deactivated</choice>
        <choice xml:lang="cs">0 – Vypnuto</choice>
    </enumChoice>
    <enumChoice choice="64 – 50 %" value="64" />
    <enumChoice choice="65 – 51 %" value="65" />
    <enumChoice choice="66 – 52 %" value="66" />
    <enumChoice choice="67 – 52 %" value="67" />
    <enumChoice choice="68 – 53 %" value="68" />
    <enumChoice choice="69 – 54 %" value="69" />
    <enumChoice choice="70 – 55 %" value="70" />
    <enumChoice choice="71 – 55 %" value="71" />
    <enumChoice choice="72 – 56 %" value="72" />
    <enumChoice choice="73 – 57 %" value="73" />
    <enumChoice choice="74 – 58 %" value="74" />
    <enumChoice choice="75 – 59 %" value="75" />
    <enumChoice choice="76 – 59 %" value="76" />
    <enumChoice choice="77 – 60 %" value="77" />
    <enumChoice choice="78 – 61 %" value="78" />
    <enumChoice choice="79 – 62 %" value="79" />
    <enumChoice choice="80 – 63 %" value="80" />
    <enumChoice choice="81 – 63 %" value="81" />
    <enumChoice choice="82 – 64 %" value="82" />
    <enumChoice choice="83 – 65 %" value="83" />
    <enumChoice choice="84 – 66 %" value="84" />
    <enumChoice choice="85 – 66 %" value="85" />
    <enumChoice choice="86 – 67 %" value="86" />
    <enumChoice choice="87 – 68 %" value="87" />
    <enumChoice choice="88 – 69 %" value="88" />
    <enumChoice choice="89 – 70 %" value="89" />
    <enumChoice choice="90 – 70 %" value="90" />
    <enumChoice choice="91 – 71 %" value="91" />
    <enumChoice choice="92 – 72 %" value="92" />
    <enumChoice choice="93 – 73 %" value="93" />
    <enumChoice choice="94 – 73 %" value="94" />
    <enumChoice choice="95 – 74 %" value="95" />
    <enumChoice choice="96 – 75 %" value="96" />
    <enumChoice choice="97 – 76 %" value="97" />
    <enumChoice choice="98 – 77 %" value="98" />
    <enumChoice choice="99 – 77 %" value="99" />
    <enumChoice choice="100 – 78 %" value="100" />
    <enumChoice choice="101 – 79 %" value="101" />
    <enumChoice choice="102 – 80 %" value="102" />
    <enumChoice choice="103 – 80 %" value="103" />
    <enumChoice choice="104 – 81 %" value="104" />
    <enumChoice choice="105 – 82 %" value="105" />
    <enumChoice choice="106 – 83 %" value="106" />
    <enumChoice choice="107 – 84 %" value="107" />
    <enumChoice choice="108 – 84 %" value="108" />
    <enumChoice choice="109 – 85 %" value="109" />
    <enumChoice choice="110 – 86 %" value="110" />
    <enumChoice choice="111 – 87 %" value="111" />
    <enumChoice choice="112 – 88 %" value="112" />
    <enumChoice choice="113 – 88 %" value="113" />
    <enumChoice choice="114 – 89 %" value="114" />
    <enumChoice choice="115 – 90 %" value="115" />
    <enumChoice choice="116 – 91 %" value="116" />
    <enumChoice choice="117 – 91 %" value="117" />
    <enumChoice choice="118 – 92 %" value="118" />
    <enumChoice choice="119 – 93 %" value="119" />
    <enumChoice choice="120 – 94 %" value="120" />
    <enumChoice choice="121 – 95 %" value="121" />
    <enumChoice choice="122 – 95 %" value="122" />
    <enumChoice choice="123 – 96 %" value="123" />
    <enumChoice choice="124 – 97 %" value="124" />
    <enumChoice choice="125 – 98 %" value="125" />
    <enumChoice choice="126 – 98 %" value="126" />
    <enumChoice choice="127 – 99 %" value="127" />
    <enumChoice choice="128 – 100 %" value="128" />
    <enumChoice choice="129 – 101 %" value="129" />
    <enumChoice choice="130 – 102 %" value="130" />
    <enumChoice choice="131 – 102 %" value="131" />
    <enumChoice choice="132 – 103 %" value="132" />
    <enumChoice choice="133 – 104 %" value="133" />
    <enumChoice choice="134 – 105 %" value="134" />
    <enumChoice choice="135 – 105 %" value="135" />
    <enumChoice choice="136 – 106 %" value="136" />
    <enumChoice choice="137 – 107 %" value="137" />
    <enumChoice choice="138 – 108 %" value="138" />
    <enumChoice choice="139 – 109 %" value="139" />
    <enumChoice choice="140 – 109 %" value="140" />
    <enumChoice choice="141 – 110 %" value="141" />
    <enumChoice choice="142 – 111 %" value="142" />
    <enumChoice choice="143 – 112 %" value="143" />
    <enumChoice choice="144 – 113 %" value="144" />
    <enumChoice choice="145 – 113 %" value="145" />
    <enumChoice choice="146 – 114 %" value="146" />
    <enumChoice choice="147 – 115 %" value="147" />
    <enumChoice choice="148 – 116 %" value="148" />
    <enumChoice choice="149 – 116 %" value="149" />
    <enumChoice choice="150 – 117 %" value="150" />
    <enumChoice choice="151 – 118 %" value="151" />
    <enumChoice choice="152 – 119 %" value="152" />
    <enumChoice choice="153 – 120 %" value="153" />
    <enumChoice choice="154 – 120 %" value="154" />
    <enumChoice choice="155 – 121 %" value="155" />
    <enumChoice choice="156 – 122 %" value="156" />
    <enumChoice choice="157 – 123 %" value="157" />
    <enumChoice choice="158 – 123 %" value="158" />
    <enumChoice choice="159 – 124 %" value="159" />
    <enumChoice choice="160 – 125 %" value="160" />
    <enumChoice choice="161 – 126 %" value="161" />
    <enumChoice choice="162 – 127 %" value="162" />
    <enumChoice choice="163 – 127 %" value="163" />
    <enumChoice choice="164 – 128 %" value="164" />
    <enumChoice choice="165 – 129 %" value="165" />
    <enumChoice choice="166 – 130 %" value="166" />
    <enumChoice choice="167 – 130 %" value="167" />
    <enumChoice choice="168 – 131 %" value="168" />
    <enumChoice choice="169 – 132 %" value="169" />
    <enumChoice choice="170 – 133 %" value="170" />
    <enumChoice choice="171 – 134 %" value="171" />
    <enumChoice choice="172 – 134 %" value="172" />
    <enumChoice choice="173 – 135 %" value="173" />
    <enumChoice choice="174 – 136 %" value="174" />
    <enumChoice choice="175 – 137 %" value="175" />
    <enumChoice choice="176 – 138 %" value="176" />
    <enumChoice choice="177 – 138 %" value="177" />
    <enumChoice choice="178 – 139 %" value="178" />
    <enumChoice choice="179 – 140 %" value="179" />
    <enumChoice choice="180 – 141 %" value="180" />
    <enumChoice choice="181 – 141 %" value="181" />
    <enumChoice choice="182 – 142 %" value="182" />
    <enumChoice choice="183 – 143 %" value="183" />
    <enumChoice choice="184 – 144 %" value="184" />
    <enumChoice choice="185 – 145 %" value="185" />
    <enumChoice choice="186 – 145 %" value="186" />
    <enumChoice choice="187 – 146 %" value="187" />
    <enumChoice choice="188 – 147 %" value="188" />
    <enumChoice choice="189 – 148 %" value="189" />
    <enumChoice choice="190 – 148 %" value="190" />
    <enumChoice choice="191 – 149 %" value="191" />
    <enumChoice choice="192 – 150 %" value="192" />
    <enumChoice choice="193 – 151 %" value="193" />
    <enumChoice choice="194 – 152 %" value="194" />
    <enumChoice choice="195 – 152 %" value="195" />
    <enumChoice choice="196 – 153 %" value="196" />
    <enumChoice choice="197 – 154 %" value="197" />
    <enumChoice choice="198 – 155 %" value="198" />
    <enumChoice choice="199 – 155 %" value="199" />
    <enumChoice choice="200 – 156 %" value="200" />
    <enumChoice choice="201 – 157 %" value="201" />
    <enumChoice choice="202 – 158 %" value="202" />
    <enumChoice choice="203 – 159 %" value="203" />
    <enumChoice choice="204 – 159 %" value="204" />
    <enumChoice choice="205 – 160 %" value="205" />
    <enumChoice choice="206 – 161 %" value="206" />
    <enumChoice choice="207 – 162 %" value="207" />
    <enumChoice choice="208 – 163 %" value="208" />
    <enumChoice choice="209 – 163 %" value="209" />
    <enumChoice choice="210 – 164 %" value="210" />
    <enumChoice choice="211 – 165 %" value="211" />
    <enumChoice choice="212 – 166 %" value="212" />
    <enumChoice choice="213 – 166 %" value="213" />
    <enumChoice choice="214 – 167 %" value="214" />
    <enumChoice choice="215 – 168 %" value="215" />
    <enumChoice choice="216 – 169 %" value="216" />
    <enumChoice choice="217 – 170 %" value="217" />
    <enumChoice choice="218 – 170 %" value="218" />
    <enumChoice choice="219 – 171 %" value="219" />
    <enumChoice choice="220 – 172 %" value="220" />
    <enumChoice choice="221 – 173 %" value="221" />
    <enumChoice choice="222 – 173 %" value="222" />
    <enumChoice choice="223 – 174 %" value="223" />
    <enumChoice choice="224 – 175 %" value="224" />
    <enumChoice choice="225 – 176 %" value="225" />
    <enumChoice choice="226 – 177 %" value="226" />
    <enumChoice choice="227 – 177 %" value="227" />
    <enumChoice choice="228 – 178 %" value="228" />
    <enumChoice choice="229 – 179 %" value="229" />
    <enumChoice choice="230 – 180 %" value="230" />
    <enumChoice choice="231 – 180 %" value="231" />
    <enumChoice choice="232 – 181 %" value="232" />
    <enumChoice choice="233 – 182 %" value="233" />
    <enumChoice choice="234 – 183 %" value="234" />
    <enumChoice choice="235 – 184 %" value="235" />
    <enumChoice choice="236 – 184 %" value="236" />
    <enumChoice choice="237 – 185 %" value="237" />
    <enumChoice choice="238 – 186 %" value="238" />
    <enumChoice choice="239 – 187 %" value="239" />
    <enumChoice choice="240 – 188 %" value="240" />
    <enumChoice choice="241 – 188 %" value="241" />
    <enumChoice choice="242 – 189 %" value="242" />
    <enumChoice choice="243 – 190 %" value="243" />
    <enumChoice choice="244 – 191 %" value="244" />
    <enumChoice choice="245 – 191 %" value="245" />
    <enumChoice choice="246 – 192 %" value="246" />
    <enumChoice choice="247 – 193 %" value="247" />
    <enumChoice choice="248 – 194 %" value="248" />
    <enumChoice choice="249 – 195 %" value="249" />
    <enumChoice choice="250 – 195 %" value="250" />
    <enumChoice choice="251 – 196 %" value="251" />
    <enumChoice choice="252 – 197 %" value="252" />
    <enumChoice choice="253 – 198 %" value="253" />
    <enumChoice choice="254 – 198 %" value="254" />
    <enumChoice choice="255 – 199 %" value="255" />
</enumVal>
