{
    "$schema": "http://json-schema.org/draft-04/schema#",
    "title": "jmri-json-client-message",
    "type": "object",
    "description": "Message from client to JMRI",
    "properties": {
        "type": {
            "type": "string",
            "description": "Data type if data is present, message type otherwise"
        },
        "data": {
            "type": "object",
            "description": "Data carried in message, see individual types for valid schemas"
        },
        "method": {
            "type": "string",
            "enum": ["get", "put", "post", "delete"],
            "description": "HTTP Method equivalent to be performed on data; defaults to \"post\" if \"data\" is present, otherwise it defaults to \"get\""
        },
        "list": {
            "type": "string",
            "description": "Request for a list of the given type; only valid with \"type\" value of \"list\""
        }
    },
    "oneOf": [
        {
            "required": ["type", "data"]
        },
        {
            "required": ["type", "list"]
        },
        {
            "required": ["type"]
        }
    ]
}
